easybake/__init__.py
easybake/__main__.py
easybake/compile.py
easybake/easybake.py
easybake-0.0.2.dist-info/LICENSE
easybake-0.0.2.dist-info/METADATA
easybake-0.0.2.dist-info/WHEEL
easybake-0.0.2.dist-info/top_level.txt
easybake-0.0.2.dist-info/RECORD
