Metadata-Version: 2.1
Name: easybake
Version: 0.0.2
Summary: A static site builder
Home-page: https://github.com/tsaylor/easybake
Author: Tim Saylor
Author-email: tim.saylor@gmail.com
License: UNKNOWN
Platform: UNKNOWN
Classifier: Programming Language :: Python :: 3
Classifier: License :: OSI Approved :: MIT License
Classifier: Operating System :: OS Independent
Requires-Python: >=3.6
Requires-Dist: Jinja2
Requires-Dist: markdown
Requires-Dist: PyYAML
